{
  "id": "csharpInterviewStacksHashing",
  "displayName": "C# Intervju 1 · Stack og hashing",
  "language": "cs",
  "entry": "submission",
  "testFile": "Tests.cs",
  "reference": "Reference.cs",
  "details": "Intervju-nivå (C#)\nStack og hashing\n\nInnsendingen skrives til Submission.cs og kompileres sammen med testfila. Du må selv definere den public kontrakten testfila refererer (ingen auto-public), og kan ikke bruke top-level statements.\n\nDisse oppgavene ligger på nivå med tekniske intervju. Poenget er å velge riktig datastruktur og bruke det du kan i nye situasjoner.\n\nImplementer klassen:\n\npublic static class Solution\n{\n    // true hvis alle parenteser i s er balansert og riktig nøstet. Gyldige tegn\n    // er (), [] og {}. Andre tegn ignoreres. IsBalanced(\"(a[b]{c})\") gir true.\n    // Tom streng gir true.\n    public static bool IsBalanced(string s);\n\n    // Indeksene [i, j] (i < j) til de to tallene som summerer til target, eller\n    // [-1, -1] hvis ingen finnes. Maks ett gyldig svar.\n    public static int[] TwoSum(int[] nums, int target);\n\n    // Grupperer ord som er anagram av hverandre. Gruppene returneres i den\n    // rekkefølgen den første forekomsten av hver gruppe dukker opp i words, og\n    // innen hver gruppe beholdes input-rekkefølgen.\n    public static string[][] GroupAnagrams(string[] words);\n}"
}
