{
  "id": "csharpInterviewDesign",
  "displayName": "C# Intervju 3 · Komposisjon og design",
  "language": "cs",
  "entry": "submission",
  "testFile": "Tests.cs",
  "reference": "Reference.cs",
  "details": "Intervju-nivå (C#)\nKomposisjon og design\n\nInnsendingen skrives til csharpInterviewDesign.cs. Du må selv definere den public kontrakten til klassen din (hva som er public), og kan ikke bruke top-level statements.\n\nNedenfor er et forslag til hvordan filen bør se ut.\n\nImplementer begge typene:\n\npublic static class Solution\n{\n    //Denne oppgaven handler om å finne overlappende intervaller.\n    //Et intervall er representert som et array av to tall.\n    // Hvert intervall er [start, slutt] med start <= slutt.\n    //Input vil være en samling av disse.\n    //Noen av intervallene vil overlappe\n    //Metoden skal slå sammen alle\n    // overlappende intervaller og returnerer resultatet sortert stigende på\n    // start. Intervaller som bare tangerer (f.eks. [1,2] og [2,3]) regnes som overlappende.\n    //Det er fordi intervallet [1,3] også dekker over [2,3]. Resultatet av en merge vil være [1,3].\n    //Et annet eksempel på overlappende intervaller er [1,3] og [2,6]. Resultatet av en merge vil være [1,6].\n    //Hvert intervall er et int-array med lengde 2.\n    public static int[][] MergeIntervals(int[][] intervals);\n}\n\n// En cache med fast kapasitet som kaster ut det minst nylig brukte elementet\n// når den er full. Både Get og Put teller som bruk.\npublic class LruCache\n{\n    public LruCache(int capacity);\n    public int Get(int key);          // verdien, eller -1 hvis nøkkelen mangler\n    public void Put(int key, int value);\n}"
}
